calval/__init__.py
calval/analysis.py
calval/azure_storage.py
calval/config.py
calval/geometry.py
calval/normalized_scene.py
calval/raster_utils.py
calval/sat_measurements.py
calval/scene_utils.py
calval/sites.py
calval/storage.py
calval/sun_locator.py
calval/providers/__init__.py
calval/providers/scene_data.py
calval/providers/scene_info.py
calval/providers/landsat/__init__.py
calval/providers/landsat/landsat_mtl.py
calval/providers/sentinel/__init__.py
calval/providers/sentinel/sentinel_xml.py
calval/satellites/Newsat3_Hyperspectral_SRF.json
calval/satellites/__init__.py
calval/satellites/multiband_srf.py
calval/satellites/srf.py
calval/site_data/baotou_poly.dbf
calval/site_data/baotou_poly.prj
calval/site_data/baotou_poly.qpj
calval/site_data/baotou_poly.shp
calval/site_data/baotou_poly.shx
calval/site_data/negev_poly.dbf
calval/site_data/negev_poly.prj
calval/site_data/negev_poly.qpj
calval/site_data/negev_poly.shp
calval/site_data/negev_poly.shx
calval/site_data/rrvalley_poly.dbf
calval/site_data/rrvalley_poly.prj
calval/site_data/rrvalley_poly.qpj
calval/site_data/rrvalley_poly.shp
calval/site_data/rrvalley_poly.shx
calval/utils/__init__.py
calval/utils/batch_plot.py
calval-0.1.8.dist-info/METADATA
calval-0.1.8.dist-info/WHEEL
calval-0.1.8.dist-info/top_level.txt
calval-0.1.8.dist-info/RECORD
