Metadata-Version: 2.1
Name: calval
Version: 0.1.8
Summary: Python package for easy radiometric calibration&validation of satellite EO payloads
Home-page: https://github.com/satellogic/calval
Author: Slava Kerner, Amit Aronovitch
Author-email: amit@satellogic.com
License: UNKNOWN
Platform: UNKNOWN
Classifier: Development Status :: 4 - Beta
Classifier: Environment :: Console
Classifier: Intended Audience :: Science/Research
Classifier: Operating System :: OS Independent
Classifier: Programming Language :: Python :: 3
Classifier: Topic :: Software Development :: Libraries :: Python Modules
Classifier: Topic :: Utilities
Requires-Dist: radcalnet (>=0.1.1)
Requires-Dist: python-dateutil
Requires-Dist: appdirs
Requires-Dist: numpy
Requires-Dist: pysolar (>=0.8)
Requires-Dist: pyspectral
Requires-Dist: matplotlib (>=2.2.3)
Requires-Dist: pandas (>=0.20)
Requires-Dist: telluric (>=0.7)
Provides-Extra: azure_storage
Requires-Dist: azure-storage-blob ; extra == 'azure_storage'
